pandas2tensorboard/__init__.py
pandas2tensorboard/pandas2tensorboard.py
pandas2tensorboard/test/__init__.py
pandas2tensorboard/test/test_transformer.py
pandas2tensorboard-0.1.1a1.dist-info/LICENSE
pandas2tensorboard-0.1.1a1.dist-info/WHEEL
pandas2tensorboard-0.1.1a1.dist-info/METADATA
pandas2tensorboard-0.1.1a1.dist-info/RECORD
